MANIFEST.in
setup.py
hermeslib/__init__.py
hermeslib/config.ini
hermeslib/config.py
hermeslib/error.py
hermeslib.egg-info/PKG-INFO
hermeslib.egg-info/SOURCES.txt
hermeslib.egg-info/dependency_links.txt
hermeslib.egg-info/requires.txt
hermeslib.egg-info/top_level.txt
hermeslib/api/__init__.py
hermeslib/api/action.py
hermeslib/api/base.py
hermeslib/api/chassis.py
hermeslib/api/module.py
hermeslib/api/port.py
hermeslib/api/stream.py
hermeslib/example/__init__.py
hermeslib/example/test2layer.py
hermeslib/example/test3layer.py
hermeslib/packaging/__init__.py
hermeslib/packaging/packet.py
hermeslib/packaging/stream.py
hermeslib/packaging/protocol/Ethernet.py
hermeslib/packaging/protocol/IPV4.py
hermeslib/packaging/protocol/TCP.py
hermeslib/packaging/protocol/UDP.py
hermeslib/packaging/protocol/__init__.py
hermeslib/packaging/protocol/base.py
hermeslib/scripts/__init__.py
hermeslib/scripts/chassis.py
hermeslib/scripts/module.py
hermeslib/scripts/port.py
hermeslib/scripts/runner.py
hermeslib/scripts/stream.py
hermeslib/util/__init__.py
hermeslib/util/common.py
hermeslib/util/file.py
hermeslib/util/logger.py
hermeslib/util/pkt.py
hermeslib/util/sock.py